relu_truncate.v
module relu_truncate #(
    parameter WIDTH = 16
)(
    input signed [2*WIDTH-1:0] accumulated, 
    output reg signed [WIDTH-1:0] out_relu
);

    always @(*) begin
        //negative check
        if (accumulated[2*WIDTH-1] == 1'b1) begin
            out_relu = 16'd0; 
        end 
        
        // positive saturation check
        else if (|accumulated[2*WIDTH-1:2*WIDTH-5] == 1'b1) begin
            out_relu = 16'h7FFF;
        end 
        
        //safe trucan
        else begin
            out_relu = accumulated[27:12];
        end
    end

endmodule

accumulator.v
module accumulator #(
    parameter WIDTH = 16
)(
    input clk,
    input rst,
    input [1:0] state_accum,
    input signed [2*WIDTH-1:0] in_accum,
    output reg signed [2*WIDTH-1:0] out_accum
);
    reg signed [2*WIDTH-1:0] accum;

    always @(posedge clk) begin
        if (rst == 1) begin
            accum <= 0;
            out_accum <= 0;
        end else begin
            case (state_accum)
                2'b00: begin //hold values
                    accum <= accum;
                    out_accum <= out_accum;
                end
                2'b01: accum <= accum + in_accum; //accumulate
                2'b10: out_accum <= accum; //output
                2'b11: accum <= 0; //clear
            endcase
        end
    end
endmodule

mux_2to1_mac.v
//a 2to1 mux with bias width adjustor
module mux_2to1_mac #(
    parameter WIDTH = 16
)(
    input signed [WIDTH-1:0] in_bias,
    input signed [2*WIDTH-1:0] in_prod,
    input sel,
    output reg signed [2*WIDTH-1:0] out_mux
);
    always @(*) begin
        case (sel)
            1'b0: out_mux = { {4{in_bias[15]}}, in_bias, 12'd0 };
            1'b1: out_mux = in_prod;
        endcase
    end
endmodule

multiplier.v
module multiplier #(
    parameter WIDTH = 16
)(
    input clk,
    input rst,
    input signed [WIDTH-1:0] w_mult,
    input signed [WIDTH-1:0] in_mult,
    output reg signed [2*WIDTH-1:0] out_mult
);
    always @(posedge clk) begin
        if (rst == 1) begin
            out_mult <= 0;
        end else begin
            out_mult <= in_mult*w_mult;
        end
    end
endmodule

MAC.v
`include "multiplier.v"
`include "mux_2to1_mac.v"
`include "accumulator.v"
`include "relu_truncate.v"

module MAC #(
    parameter WIDTH = 16
)(
    input clk,
    input rst,

    input signed [WIDTH-1:0] w_mac,
    input signed [WIDTH-1:0] in_mac,
    input signed [WIDTH-1:0] bias_mac,
    output signed [WIDTH-1:0] out_mac,

    input sel_mux,
    input [1:0] state
);
    wire signed [2*WIDTH-1:0] mult_mux;
    wire signed [2*WIDTH-1:0] mux_accum;
    wire signed [2*WIDTH-1:0] accum_relu;

    multiplier #( .WIDTH(WIDTH) ) u_mult(
        .clk(clk),
        .rst(rst),
        .w_mult(w_mac),
        .in_mult(in_mac),
        .out_mult(mult_mux)
    );

    mux_2to1_mac #( .WIDTH(WIDTH) ) u_mux(
        .in_bias(bias_mac),
        .in_prod(mult_mux),
        .sel(sel_mux),
        .out_mux(mux_accum)
    );

    accumulator #( .WIDTH(WIDTH) ) u_accum(
        .clk(clk),
        .rst(rst),
        .state_accum(state),
        .in_accum(mux_accum),
        .out_accum(accum_relu)
    );

    relu_truncate #( .WIDTH(WIDTH) ) u_relu(
        .accumulated(accum_relu), 
        .out_relu(out_mac)
    );
endmodule

tb_MAC.v
`timescale 1ns/1ps
`include "MAC.v"

module tb_mac #(
    parameter WIDTH = 16
);
    reg clk;
    reg rst;

    reg signed [WIDTH-1:0] w_mac;
    reg signed [WIDTH-1:0] in_mac;
    reg signed [WIDTH-1:0] bias_mac;
    wire signed [WIDTH-1:0] out_mac;

    reg sel_mux;
    reg [1:0] state;

    MAC dut(
        .clk(clk),
        .rst(rst),
        .w_mac(w_mac),
        .in_mac(in_mac),
        .bias_mac(bias_mac),
        .out_mac(out_mac),
        .sel_mux(sel_mux),
        .state(state)
    );

    initial begin
        clk = 0;
        forever #5 clk = ~clk;
    end

    initial begin
        $dumpfile("mac_test.vcd");
        $dumpvars(0, tb_mac);

        w_mac = 0; in_mac = 0;  bias_mac = 0;
        sel_mux = 0; state = 2'b00; 
        rst = 1;

        repeat(5) @(posedge clk);
        #1; 
        rst = 0;

        w_mac = 16'd4096;  in_mac = 16'd2048;   
        bias_mac = 16'd4096;                    
        sel_mux = 1'b0;                         
        state = 2'b01;                          
        @(posedge clk); #1;

        w_mac = -16'd4096; in_mac = 16'd2048;   
        sel_mux = 1'b1;                         
        state = 2'b01;                          
        @(posedge clk); #1;

        w_mac = 16'd2048;  in_mac = 16'd2048;   
        sel_mux = 1'b1;
        state = 2'b01;                          
        @(posedge clk); #1;

        w_mac = 16'd4096;  in_mac = -16'd4096;  
        sel_mux = 1'b1;
        state = 2'b01;                          
        @(posedge clk); #1;

        w_mac = 16'd0;     in_mac = 16'd0;      
        sel_mux = 1'b1;
        state = 2'b01;                          
        @(posedge clk); #1;

        state = 2'b10;                          
        @(posedge clk); #1;

        state = 2'b11;                          
        @(posedge clk); #1;

        state = 2'b00;                          
        repeat(3) @(posedge clk);

        $display("final MAC Output: %d", out_mac);
        $finish;
    end

endmodule

waveform/mac_test.vcd
$date
	Sat Feb 28 19:39:42 2026
$end
$version
	Icarus Verilog
$end
$timescale
	1ps
$end
$scope module tb_mac $end
$var wire 16 ! out_mac [15:0] $end
$var parameter 32 " WIDTH $end
$var reg 16 # bias_mac [15:0] $end
$var reg 1 $ clk $end
$var reg 16 % in_mac [15:0] $end
$var reg 1 & rst $end
$var reg 1 ' sel_mux $end
$var reg 2 ( state [1:0] $end
$var reg 16 ) w_mac [15:0] $end
$scope module dut $end
$var wire 16 * bias_mac [15:0] $end
$var wire 1 $ clk $end
$var wire 16 + in_mac [15:0] $end
$var wire 1 & rst $end
$var wire 1 ' sel_mux $end
$var wire 2 , state [1:0] $end
$var wire 16 - w_mac [15:0] $end
$var wire 16 . out_mac [15:0] $end
$var wire 32 / mux_accum [31:0] $end
$var wire 32 0 mult_mux [31:0] $end
$var wire 32 1 accum_relu [31:0] $end
$var parameter 32 2 WIDTH $end
$scope module u_accum $end
$var wire 1 $ clk $end
$var wire 1 & rst $end
$var wire 2 3 state_accum [1:0] $end
$var wire 32 4 in_accum [31:0] $end
$var parameter 32 5 WIDTH $end
$var reg 32 6 accum [31:0] $end
$var reg 32 7 out_accum [31:0] $end
$upscope $end
$scope module u_mult $end
$var wire 1 $ clk $end
$var wire 16 8 in_mult [15:0] $end
$var wire 1 & rst $end
$var wire 16 9 w_mult [15:0] $end
$var parameter 32 : WIDTH $end
$var reg 32 ; out_mult [31:0] $end
$upscope $end
$scope module u_mux $end
$var wire 16 < in_bias [15:0] $end
$var wire 32 = in_prod [31:0] $end
$var wire 1 ' sel $end
$var parameter 32 > WIDTH $end
$var reg 32 ? out_mux [31:0] $end
$upscope $end
$scope module u_relu $end
$var wire 32 @ accumulated [31:0] $end
$var parameter 32 A WIDTH $end
$var reg 16 B out_relu [15:0] $end
$upscope $end
$upscope $end
$upscope $end
$enddefinitions $end
$comment Show the parameter values. $end
$dumpall
b10000 A
b10000 >
b10000 :
b10000 5
b10000 2
b10000 "
$end
#0
$dumpvars
bx B
bx @
b0 ?
bx =
b0 <
bx ;
b0 9
b0 8
bx 7
bx 6
b0 4
b0 3
bx 1
bx 0
b0 /
bx .
b0 -
b0 ,
b0 +
b0 *
b0 )
b0 (
0'
1&
b0 %
0$
b0 #
bx !
$end
#5000
b0 !
b0 .
b0 B
b0 0
b0 ;
b0 =
b0 1
b0 7
b0 @
b0 6
1$
#10000
0$
#15000
1$
#20000
0$
#25000
1$
#30000
0$
#35000
1$
#40000
0$
#45000
1$
#46000
b1000000000000000000000000 /
b1000000000000000000000000 4
b1000000000000000000000000 ?
b1 (
b1 ,
b1 3
b1000000000000 #
b1000000000000 *
b1000000000000 <
b100000000000 %
b100000000000 +
b100000000000 8
b1000000000000 )
b1000000000000 -
b1000000000000 9
0&
#50000
0$
#55000
b1000000000000000000000000 6
b100000000000000000000000 0
b100000000000000000000000 ;
b100000000000000000000000 =
1$
#56000
b100000000000000000000000 /
b100000000000000000000000 4
b100000000000000000000000 ?
1'
b1111000000000000 )
b1111000000000000 -
b1111000000000000 9
#60000
0$
#65000
b11111111100000000000000000000000 /
b11111111100000000000000000000000 4
b11111111100000000000000000000000 ?
b11111111100000000000000000000000 0
b11111111100000000000000000000000 ;
b11111111100000000000000000000000 =
b1100000000000000000000000 6
1$
#66000
b100000000000 )
b100000000000 -
b100000000000 9
#70000
0$
#75000
b10000000000000000000000 /
b10000000000000000000000 4
b10000000000000000000000 ?
b1000000000000000000000000 6
b10000000000000000000000 0
b10000000000000000000000 ;
b10000000000000000000000 =
1$
#76000
b1111000000000000 %
b1111000000000000 +
b1111000000000000 8
b1000000000000 )
b1000000000000 -
b1000000000000 9
#80000
0$
#85000
b11111111000000000000000000000000 /
b11111111000000000000000000000000 4
b11111111000000000000000000000000 ?
b11111111000000000000000000000000 0
b11111111000000000000000000000000 ;
b11111111000000000000000000000000 =
b1010000000000000000000000 6
1$
#86000
b0 %
b0 +
b0 8
b0 )
b0 -
b0 9
#90000
0$
#95000
b0 /
b0 4
b0 ?
b10000000000000000000000 6
b0 0
b0 ;
b0 =
1$
#96000
b10 (
b10 ,
b10 3
#100000
0$
#105000
b10000000000 !
b10000000000 .
b10000000000 B
b10000000000000000000000 1
b10000000000000000000000 7
b10000000000000000000000 @
1$
#106000
b11 (
b11 ,
b11 3
#110000
0$
#115000
b0 6
1$
#116000
b0 (
b0 ,
b0 3
