controller.v
module controller (
    input clk,
    input start,
    input stop,
    input rst,

    //control mux input (external input vs BRAM input)
    output reg sel_mux_in,
    
    //control ROM
    output reg en_out,
    output reg [5:0] w_addr, //Accommodates weights 0 to 39
    output reg [5:0] b_addr, //40 to 48

    //control BRAM
    output reg en_store,
    output reg en_fetch,
    output reg [2:0] mem_store_addr,
    output reg [2:0] mem_fetch_addr,

    //control MAC
    output reg sel_mux_mac,
    output reg [1:0] state_accum,
    
    //control DeMux (BRAM vs system output)
    output reg sel_demux
);

    localparam BIAS_START = 6'd40;

    localparam MAC_HOLD  = 2'b00; 
    localparam MAC_ACCUM = 2'b01; 
    localparam MAC_OUT   = 2'b10; 
    localparam MAC_CLEAR = 2'b11; 

    reg [6:0] cycle;
    reg [2:0] step; 
    reg running;

    always @(posedge clk) begin
        if (rst) begin
            cycle          <= 1;
            step           <= 1;
            running        <= 0;
            
            sel_mux_in     <= 0;
            sel_mux_mac    <= 0;
            sel_demux      <= 0;
            
            en_out         <= 0;
            w_addr         <= 0;
            b_addr         <= BIAS_START;
            
            en_store       <= 0;
            en_fetch       <= 0;
            mem_store_addr <= 0;
            mem_fetch_addr <= 0;
            
            state_accum    <= MAC_CLEAR; 
        end else begin
            //active low logic
            if (~start) running <= 1'b1;
            if (~stop)  running <= 1'b0;

            if (running) begin
                if (cycle < 68) cycle <= cycle + 1; 
                en_store <= 0;
                en_fetch <= 0;
                en_out   <= 1; 

                // ==========================================
                // LAYER 1: Cycles 1 to 56 
                // ==========================================
                if (cycle >= 1 && cycle <= 56) begin 
                    sel_mux_in <= 1'b0; 
                    sel_demux  <= 1'b0; 

                    case (step)
                        1: begin
                            state_accum <= MAC_ACCUM; 
                            sel_mux_mac <= 1'b0; // Select Bias
                            step        <= step + 1;
                            if (cycle > 2) mem_store_addr <= mem_store_addr + 1;
                        end
                        2, 3, 4, 5: begin 
                            state_accum <= MAC_ACCUM;
                            sel_mux_mac <= 1'b1; // Select Product
                            w_addr      <= w_addr + 1;
                            step        <= step + 1;
                        end
                        6: begin 
                            state_accum <= MAC_OUT;
                            step        <= step + 1;
                        end
                        7: begin 
                            state_accum <= MAC_CLEAR; 
                            en_store    <= 1;
                            b_addr      <= b_addr + 1; 
                            step        <= 1;          
                        end
                    endcase
                end

                // ==========================================
                // LAYER 2: Cycles 57 to 67 
                // ==========================================
                else if (cycle >= 57 && cycle <= 67) begin
                    sel_mux_in <= 1'b1; 
                    sel_demux  <= 1'b1; 
                    
                    if (cycle == 57) begin // Prep Cycle 58: Load Bias 9
                        state_accum    <= MAC_ACCUM; 
                        sel_mux_mac    <= 1'b0; 
                        en_fetch       <= 1;
                        mem_fetch_addr <= 0;
                    end 
                    else if (cycle >= 58 && cycle <= 64) begin // Prep Cycles 59-65: MAC
                        state_accum    <= MAC_ACCUM;
                        sel_mux_mac    <= 1'b1; 
                        en_fetch       <= 1;
                        mem_fetch_addr <= mem_fetch_addr + 1;
                        w_addr         <= w_addr + 1;
                    end 
                    else if (cycle == 65) begin // Prep Cycle 66: Final MAC
                        state_accum    <= MAC_ACCUM;
                        sel_mux_mac    <= 1'b1; 
                        en_fetch       <= 0; 
                        w_addr         <= w_addr + 1;
                    end 
                    else if (cycle == 66) begin // Prep Cycle 67: Wait / Latch
                        state_accum    <= MAC_OUT;
                    end 
                    else if (cycle == 67) begin // Prep Cycle 68: Clear
                        state_accum    <= MAC_CLEAR; 
                    end
                end 

                // ==========================================
                // DONE / END
                // ==========================================
                else begin
                    state_accum <= MAC_HOLD;
                    sel_demux   <= 1'b1; // Keep demux open so sys_out holds the final value
                    en_out      <= 0;
                    running     <= 0; 
                end
            end
        end
    end

endmodule

demux_1to2.v
module demux_1to2 #(
    parameter WIDTH = 16
)(
    input signed [WIDTH-1:0] in_data,
    input sel, // 0 = send to BRAM, 1 = send to System Output
    output reg signed [WIDTH-1:0] out_bram,
    output reg signed [WIDTH-1:0] out_sys
);
    always @(*) begin
        if (sel == 1'b0) begin
            out_bram = in_data;
            out_sys  = 0;
        end else begin
            out_bram = 0;
            out_sys  = in_data;
        end
    end
endmodule

mux_2to1_in.v
module mux_2to1_in #(
    parameter WIDTH = 16
)(
    input signed [WIDTH-1:0] in_ext,
    input signed [WIDTH-1:0] in_bram,
    input sel,
    output reg signed [WIDTH-1:0] out_mux
);
    always @(*) begin
        case (sel)
            1'b0: out_mux = in_ext; 
            1'b1: out_mux = in_bram; 
        endcase
    end
endmodule

bram.v
//bram that stores mac output
module bram #(
    parameter WIDTH = 16
)(
    input clk,
    input rst,
    
    input en_store,
    input en_fetch,
    input [2:0] mem_store_addr, //can store up to 8 data
    input [2:0] mem_fetch_addr,

    input signed [WIDTH-1:0] store,
    output reg signed [WIDTH-1:0] fetch
);
    //memory array
    reg signed [WIDTH-1:0] bram_memory [0:8];
    integer i;

    always @(posedge clk) begin
        if (rst) begin
            for (i=0; i<8 ; i=i+1) begin
                bram_memory[i] <= 0;
            end
            fetch <= 0;
        end else begin
            if (en_store) begin
                bram_memory[mem_store_addr] <= store;
            end

            if (en_fetch) begin
                fetch <= bram_memory[mem_fetch_addr];
            end
        end
    end
endmodule

rom.v
//ROM that stores weight and bias
module rom#(
    parameter WIDTH = 16
)(
    input clk,
    input en_out,
    input [5:0] w_addr,
    input [5:0] b_addr,
    output reg signed [WIDTH-1:0] w_val,
    output reg signed [WIDTH-1:0] b_val
);
    //memory array
    reg signed [WIDTH-1:0] rom_memory [0:48];
    
    initial begin
        $readmemh("weight_bias.mem", rom_memory);
    end

    always @(posedge clk) begin
        if (en_out) begin
            w_val <= rom_memory[w_addr];
            b_val <= rom_memory[b_addr];
        end else begin
            w_val <= 0;
            b_val <= 0;
        end
    end
endmodule

relu_truncate.v
module relu_truncate #(
    parameter WIDTH = 16
)(
    input signed [2*WIDTH-1:0] accumulated, 
    output reg signed [WIDTH-1:0] out_relu
);

    always @(*) begin
        //negative check
        if (accumulated[2*WIDTH-1] == 1'b1) begin
            out_relu = 16'd0; 
        end 
        
        // positive saturation check
        else if (|accumulated[2*WIDTH-1:2*WIDTH-5] == 1'b1) begin
            out_relu = 16'h7FFF;
        end 
        
        //safe trucan
        else begin
            out_relu = accumulated[27:12];
        end
    end

endmodule

accumulator.v
module accumulator #(
    parameter WIDTH = 16
)(
    input clk,
    input rst,
    input [1:0] state_accum,
    input signed [2*WIDTH-1:0] in_accum,
    output reg signed [2*WIDTH-1:0] out_accum
);
    reg signed [2*WIDTH-1:0] accum;

    always @(posedge clk) begin
        if (rst == 1) begin
            accum <= 0;
            out_accum <= 0;
        end else begin
            case (state_accum)
                2'b00: begin //hold values
                    accum <= accum;
                    out_accum <= out_accum;
                end
                2'b01: accum <= accum + in_accum; //accumulate
                2'b10: out_accum <= accum; //output
                2'b11: accum <= 0; //clear
            endcase
        end
    end
endmodule

mux_2to1_mac.v
//a 2to1 mux with bias width adjustor
module mux_2to1_mac #(
    parameter WIDTH = 16
)(
    input signed [WIDTH-1:0] in_bias,
    input signed [2*WIDTH-1:0] in_prod,
    input sel,
    output reg signed [2*WIDTH-1:0] out_mux
);
    always @(*) begin
        case (sel)
            1'b0: out_mux = { {4{in_bias[15]}}, in_bias, 12'd0 };
            1'b1: out_mux = in_prod;
        endcase
    end
endmodule

multiplier.v
module multiplier #(
    parameter WIDTH = 16
)(
    input clk,
    input rst,
    input signed [WIDTH-1:0] w_mult,
    input signed [WIDTH-1:0] in_mult,
    output reg signed [2*WIDTH-1:0] out_mult
);
    always @(posedge clk) begin
        if (rst == 1) begin
            out_mult <= 0;
        end else begin
            out_mult <= in_mult*w_mult;
        end
    end
endmodule

MAC.v
`include "multiplier.v"
`include "mux_2to1_mac.v"
`include "accumulator.v"
`include "relu_truncate.v"

module MAC #(
    parameter WIDTH = 16
)(
    input clk,
    input rst,

    input signed [WIDTH-1:0] w_mac,
    input signed [WIDTH-1:0] in_mac,
    input signed [WIDTH-1:0] bias_mac,
    output signed [WIDTH-1:0] out_mac,

    input sel_mux,
    input [1:0] state
);
    wire signed [2*WIDTH-1:0] mult_mux;
    wire signed [2*WIDTH-1:0] mux_accum;
    wire signed [2*WIDTH-1:0] accum_relu;

    multiplier #( .WIDTH(WIDTH) ) u_mult(
        .clk(clk),
        .rst(rst),
        .w_mult(w_mac),
        .in_mult(in_mac),
        .out_mult(mult_mux)
    );

    mux_2to1_mac #( .WIDTH(WIDTH) ) u_mux(
        .in_bias(bias_mac),
        .in_prod(mult_mux),
        .sel(sel_mux),
        .out_mux(mux_accum)
    );

    accumulator #( .WIDTH(WIDTH) ) u_accum(
        .clk(clk),
        .rst(rst),
        .state_accum(state),
        .in_accum(mux_accum),
        .out_accum(accum_relu)
    );

    relu_truncate #( .WIDTH(WIDTH) ) u_relu(
        .accumulated(accum_relu), 
        .out_relu(out_mac)
    );
endmodule

top_level.v
`include "MAC.v"
`include "rom.v"
`include "bram.v"
`include "mux_2to1_in.v"
`include "demux_1to2.v"
`include "controller.v"

module top_level#(
    parameter WIDTH = 16
)(
    input clk,
    input rst,
    input start,
    input stop,

    input signed [WIDTH-1:0] sys_in,
    output signed [WIDTH-1:0] sys_out
);
    //INERNAL WIRE
    wire signed [WIDTH-1:0] mux_mac, mac_demux; //IO MAC
    wire signed [WIDTH-1:0] rom_mac_w, rom_mac_b; //weight and bias MAC
    wire cntrl_mac_sel;
    wire [1:0] cntrl_mac_state;
    
    wire cntrl_rom_en_out;
    wire [5:0] cntrl_rom_w_addr;
    wire [5:0] cntrl_rom_b_addr;

    wire cntrl_bram_en_fetch;
    wire cntrl_bram_en_store;
    wire [2:0] cntrl_bram_store_addr;
    wire [2:0] cntrl_bram_fetch_addr;
    wire signed [WIDTH-1:0] bram_mux, demux_bram;

    wire cntrl_mux_in;
    wire cntrl_demux;
    
    //instantiate modules
    MAC #( .WIDTH(WIDTH) ) u_mac(
        .clk(clk),
        .rst(rst),

        .w_mac(rom_mac_w),
        .in_mac(mux_mac),
        .bias_mac(rom_mac_b),
        .out_mac(mac_demux),

        .sel_mux(cntrl_mac_sel),
        .state(cntrl_mac_state)
    );

    rom #( .WIDTH(WIDTH) ) u_rom(
        .clk(clk),
        .en_out(cntrl_rom_en_out),
        .w_addr(cntrl_rom_w_addr),
        .b_addr(cntrl_rom_b_addr),
        .w_val(rom_mac_w),
        .b_val(rom_mac_b)
    );

    bram #( .WIDTH(WIDTH) ) u_bram(
        .clk(clk),
        .rst(rst),
    
        .en_store(cntrl_bram_en_store),
        .en_fetch(cntrl_bram_en_fetch),
        .mem_store_addr(cntrl_bram_store_addr),
        .mem_fetch_addr(cntrl_bram_fetch_addr),

        .store(demux_bram),
        .fetch(bram_mux)
    );

    mux_2to1_in #( .WIDTH(WIDTH) ) u_mux_in(
        .in_ext(sys_in),
        .in_bram(bram_mux),
        .sel(cntrl_mux_in),
        .out_mux(mux_mac)
    );

    demux_1to2 #( .WIDTH(WIDTH) ) u_demux(
        .in_data(mac_demux),
        .sel(cntrl_demux), 
        .out_bram(demux_bram),
        .out_sys(sys_out)
    );

    controller u_controller(
        .clk(clk),
        .start(start),
        .stop(stop),
        .rst(rst),

        //control mux input (external input vs BRAM input)
        .sel_mux_in(cntrl_mux_in),
        
        //control ROM
        .en_out(cntrl_rom_en_out),
        .w_addr(cntrl_rom_w_addr), //Accommodates weights 0 to 39
        .b_addr(cntrl_rom_b_addr), //40 to 48

        //control BRAM
        .en_store(cntrl_bram_en_store),
        .en_fetch(cntrl_bram_en_fetch),
        .mem_store_addr(cntrl_bram_store_addr),
        .mem_fetch_addr(cntrl_bram_fetch_addr),

        //control MAC
        .sel_mux_mac(cntrl_mac_sel),
        .state_accum(cntrl_mac_state),
        
        //control DeMux (BRAM vs system output)
        .sel_demux(cntrl_demux)
    );
endmodule

tb_top_level.v
`timescale 1ns / 1ps
`include "top_level.v"

module tb_top_level();
    parameter WIDTH = 16;
    reg clk;
    reg rst;
    reg start;
    reg stop;
    reg signed [WIDTH-1:0] sys_in;

    wire signed [WIDTH-1:0] sys_out;

    integer i;
    reg signed [WIDTH-1:0] features [0:3]; // Array to hold the 4 input features
    integer cycle_count;

    // Instantiate the Unit Under Test (UUT)
    top_level #( .WIDTH(WIDTH) ) uut (
        .clk(clk),
        .rst(rst),
        .start(start),
        .stop(stop),
        .sys_in(sys_in),
        .sys_out(sys_out)
    );

    // Clock Generation (10ns period / 100MHz)
    initial begin
        clk = 0;
        forever #5 clk = ~clk; 
    end

    // Cycle Counter for debugging
    initial begin
        cycle_count = 0;
        forever @(posedge clk) begin
            if (!rst && !start) cycle_count = 1;
            else if (cycle_count > 0 && cycle_count < 70) cycle_count = cycle_count + 1;
        end
    end

    // Main Stimulus Block
    initial begin
        $dumpfile("top_level.vcd");
        $dumpvars(0, tb_top_level);
        //initialize inputs
        rst = 1;
        start = 1; //active low
        stop = 1;  //active low
        sys_in = 0;

        //load data
        features[0] = 16'h0100;  //Speed_ref
        features[1] = 16'h03BA;  //Speed
        features[2] = 16'h0894;  //Current
        features[3] = 16'h09B0;  //Bus_voltage

        #20;
        rst = 0;
        #10;

        //trigger start
        @(posedge clk);
        start = 0; 
        @(posedge clk);
        start = 1; 

        //feed layer input 1
        for (i = 0; i < 8; i = i + 1) begin
            //cycle 2
            @(posedge clk); 
            sys_in = features[0];
            
            // xycle 2
            @(posedge clk); 
            sys_in = features[1];
            
            // cycle 3
            @(posedge clk); 
            sys_in = features[2]; // Set up Feature 3
            
            // cycle 4
            @(posedge clk); 
            sys_in = features[3]; // Set up Feature 4
            
            //cycle 5
            @(posedge clk); 
            sys_in = 16'h0000;    // Clear input
            
            //cycle 6
            @(posedge clk); 
            
            //cycle 7 
            @(posedge clk); 
        end

        //wait for Layer 2 to finish
        wait(cycle_count == 68); 

        // 6. Display Result
        $display("-------------------------------------------------");
        $display("Inference Complete at Cycle %0d", cycle_count);
        $display("Final System Output (sys_out): %h", sys_out);
        $display("-------------------------------------------------");

        //padding before ending the simulation
        #50;
        $finish;
    end

    //monitor key signals
    initial begin
        $monitor("Time=%0t | Cycle=%0d | MAC State=%b | W_Addr=%0d | B_Addr=%0d | sys_in=%h | sys_out=%h", 
                 $time, cycle_count, uut.u_controller.state_accum, uut.cntrl_rom_w_addr, uut.cntrl_rom_b_addr, sys_in, sys_out);
    end

endmodule

waveform/top_level.vcd
$date
	Sun Mar 01 10:12:36 2026
$end
$version
	Icarus Verilog
$end
$timescale
	1ps
$end
$scope module tb_top_level $end
$var wire 16 ! sys_out [15:0] $end
$var parameter 32 " WIDTH $end
$var reg 1 # clk $end
$var reg 1 $ rst $end
$var reg 1 % start $end
$var reg 1 & stop $end
$var reg 16 ' sys_in [15:0] $end
$var integer 32 ( cycle_count [31:0] $end
$var integer 32 ) i [31:0] $end
$scope module uut $end
$var wire 1 # clk $end
$var wire 1 $ rst $end
$var wire 1 % start $end
$var wire 1 & stop $end
$var wire 16 * sys_in [15:0] $end
$var wire 16 + sys_out [15:0] $end
$var wire 16 , rom_mac_w [15:0] $end
$var wire 16 - rom_mac_b [15:0] $end
$var wire 16 . mux_mac [15:0] $end
$var wire 16 / mac_demux [15:0] $end
$var wire 16 0 demux_bram [15:0] $end
$var wire 6 1 cntrl_rom_w_addr [5:0] $end
$var wire 1 2 cntrl_rom_en_out $end
$var wire 6 3 cntrl_rom_b_addr [5:0] $end
$var wire 1 4 cntrl_mux_in $end
$var wire 2 5 cntrl_mac_state [1:0] $end
$var wire 1 6 cntrl_mac_sel $end
$var wire 1 7 cntrl_demux $end
$var wire 3 8 cntrl_bram_store_addr [2:0] $end
$var wire 3 9 cntrl_bram_fetch_addr [2:0] $end
$var wire 1 : cntrl_bram_en_store $end
$var wire 1 ; cntrl_bram_en_fetch $end
$var wire 16 < bram_mux [15:0] $end
$var parameter 32 = WIDTH $end
$scope module u_bram $end
$var wire 1 # clk $end
$var wire 1 $ rst $end
$var wire 16 > store [15:0] $end
$var wire 3 ? mem_store_addr [2:0] $end
$var wire 3 @ mem_fetch_addr [2:0] $end
$var wire 1 : en_store $end
$var wire 1 ; en_fetch $end
$var parameter 32 A WIDTH $end
$var reg 16 B fetch [15:0] $end
$var integer 32 C i [31:0] $end
$upscope $end
$scope module u_controller $end
$var wire 1 # clk $end
$var wire 1 $ rst $end
$var wire 1 % start $end
$var wire 1 & stop $end
$var parameter 6 D BIAS_START $end
$var parameter 2 E MAC_ACCUM $end
$var parameter 2 F MAC_CLEAR $end
$var parameter 2 G MAC_HOLD $end
$var parameter 2 H MAC_OUT $end
$var reg 6 I b_addr [5:0] $end
$var reg 7 J cycle [6:0] $end
$var reg 1 ; en_fetch $end
$var reg 1 2 en_out $end
$var reg 1 : en_store $end
$var reg 3 K mem_fetch_addr [2:0] $end
$var reg 3 L mem_store_addr [2:0] $end
$var reg 1 M running $end
$var reg 1 7 sel_demux $end
$var reg 1 4 sel_mux_in $end
$var reg 1 6 sel_mux_mac $end
$var reg 2 N state_accum [1:0] $end
$var reg 3 O step [2:0] $end
$var reg 6 P w_addr [5:0] $end
$upscope $end
$scope module u_demux $end
$var wire 1 7 sel $end
$var wire 16 Q in_data [15:0] $end
$var parameter 32 R WIDTH $end
$var reg 16 S out_bram [15:0] $end
$var reg 16 T out_sys [15:0] $end
$upscope $end
$scope module u_mac $end
$var wire 1 # clk $end
$var wire 1 $ rst $end
$var wire 1 6 sel_mux $end
$var wire 2 U state [1:0] $end
$var wire 16 V w_mac [15:0] $end
$var wire 16 W out_mac [15:0] $end
$var wire 32 X mux_accum [31:0] $end
$var wire 32 Y mult_mux [31:0] $end
$var wire 16 Z in_mac [15:0] $end
$var wire 16 [ bias_mac [15:0] $end
$var wire 32 \ accum_relu [31:0] $end
$var parameter 32 ] WIDTH $end
$scope module u_accum $end
$var wire 1 # clk $end
$var wire 1 $ rst $end
$var wire 2 ^ state_accum [1:0] $end
$var wire 32 _ in_accum [31:0] $end
$var parameter 32 ` WIDTH $end
$var reg 32 a accum [31:0] $end
$var reg 32 b out_accum [31:0] $end
$upscope $end
$scope module u_mult $end
$var wire 1 # clk $end
$var wire 1 $ rst $end
$var wire 16 c w_mult [15:0] $end
$var wire 16 d in_mult [15:0] $end
$var parameter 32 e WIDTH $end
$var reg 32 f out_mult [31:0] $end
$upscope $end
$scope module u_mux $end
$var wire 32 g in_prod [31:0] $end
$var wire 1 6 sel $end
$var wire 16 h in_bias [15:0] $end
$var parameter 32 i WIDTH $end
$var reg 32 j out_mux [31:0] $end
$upscope $end
$scope module u_relu $end
$var wire 32 k accumulated [31:0] $end
$var parameter 32 l WIDTH $end
$var reg 16 m out_relu [15:0] $end
$upscope $end
$upscope $end
$scope module u_mux_in $end
$var wire 16 n in_bram [15:0] $end
$var wire 16 o in_ext [15:0] $end
$var wire 1 4 sel $end
$var parameter 32 p WIDTH $end
$var reg 16 q out_mux [15:0] $end
$upscope $end
$scope module u_rom $end
$var wire 6 r b_addr [5:0] $end
$var wire 1 # clk $end
$var wire 1 2 en_out $end
$var wire 6 s w_addr [5:0] $end
$var parameter 32 t WIDTH $end
$var reg 16 u b_val [15:0] $end
$var reg 16 v w_val [15:0] $end
$upscope $end
$upscope $end
$upscope $end
$enddefinitions $end
$comment Show the parameter values. $end
$dumpall
b10000 t
b10000 p
b10000 l
b10000 i
b10000 e
b10000 `
b10000 ]
b10000 R
b10 H
b0 G
b11 F
b1 E
b101000 D
b10000 A
b10000 =
b10000 "
$end
#0
$dumpvars
bx v
bx u
bx s
bx r
bx q
b0 o
bx n
bx m
bx k
bx j
bx h
bx g
bx f
bx d
bx c
bx b
bx a
bx _
bx ^
bx \
bx [
bx Z
bx Y
bx X
bx W
bx V
bx U
bx T
bx S
bx Q
bx P
bx O
bx N
xM
bx L
bx K
bx J
bx I
bx C
bx B
bx @
bx ?
bx >
bx <
x;
x:
bx 9
bx 8
x7
x6
bx 5
x4
bx 3
x2
bx 1
bx 0
bx /
bx .
bx -
bx ,
bx +
b0 *
bx )
b0 (
b0 '
1&
1%
1$
0#
bx !
$end
#5000
b0 0
b0 >
b0 S
b0 /
b0 Q
b0 W
b0 m
b0 !
b0 +
b0 T
b0 X
b0 _
b0 j
b0 .
b0 Z
b0 d
b0 q
b0 Y
b0 f
b0 g
b0 \
b0 b
b0 k
b0 a
b0 -
b0 [
b0 h
b0 u
b0 ,
b0 V
b0 c
b0 v
b0 <
b0 B
b0 n
b11 5
b11 N
b11 U
b11 ^
b0 9
b0 @
b0 K
b0 8
b0 ?
b0 L
0;
0:
b101000 3
b101000 I
b101000 r
b0 1
b0 P
b0 s
02
07
06
04
0M
b1 O
b1 J
b1000 C
1#
#10000
0#
#15000
b1000 C
1#
#20000
0#
0$
#25000
1#
#30000
0#
#35000
1M
b1 (
0%
1#
#40000
0#
#45000
b10 O
b1 5
b1 N
b1 U
b1 ^
12
b10 J
b0 )
1%
1#
#50000
0#
#55000
b11 O
b1 1
b1 P
b1 s
16
b11 J
b111000010 -
b111000010 [
b111000010 h
b111000010 u
b1000101000 ,
b1000101000 V
b1000101000 c
b1000101000 v
b100000000 .
b100000000 Z
b100000000 d
b100000000 q
b10 (
b100000000 '
b100000000 *
b100000000 o
1#
#60000
0#
#65000
b100010100000000000 X
b100010100000000000 _
b100010100000000000 j
b100010100000000000 Y
b100010100000000000 f
b100010100000000000 g
b11000000001 ,
b11000000001 V
b11000000001 c
b11000000001 v
b100 O
b10 1
b10 P
b10 s
b100 J
b1110111010 .
b1110111010 Z
b1110111010 d
b1110111010 q
b1110111010 '
b1110111010 *
b1110111010 o
b11 (
1#
#70000
0#
#75000
b101100101111110111010 X
b101100101111110111010 _
b101100101111110111010 j
b101 O
b11 1
b11 P
b11 s
b101 J
b100010001010 ,
b100010001010 V
b100010001010 c
b100010001010 v
b100010100000000000 a
b101100101111110111010 Y
b101100101111110111010 f
b101100101111110111010 g
b100010010100 .
b100010010100 Z
b100010010100 d
b100010010100 q
b100 (
b100010010100 '
b100010010100 *
b100010010100 o
1#
#80000
0#
#85000
b10010010011111111001000 X
b10010010011111111001000 _
b10010010011111111001000 j
b10010010011111111001000 Y
b10010010011111111001000 f
b10010010011111111001000 g
b110001000011110111010 a
b1111011111110100 ,
b1111011111110100 V
b1111011111110100 c
b1111011111110100 v
b110 O
b100 1
b100 P
b100 s
b110 J
b100110110000 .
b100110110000 Z
b100110110000 d
b100110110000 q
b100110110000 '
b100110110000 *
b100110110000 o
b101 (
1#
#90000
0#
#95000
b11111111101100100000101111000000 X
b11111111101100100000101111000000 _
b11111111101100100000101111000000 j
b111 O
b10 5
b10 N
b10 U
b10 ^
b111 J
b1111100111110010 ,
b1111100111110010 V
b1111100111110010 c
b1111100111110010 v
b11000011100011110000010 a
b11111111101100100000101111000000 Y
b11111111101100100000101111000000 f
b11111111101100100000101111000000 g
b0 .
b0 Z
b0 d
b0 q
b110 (
b0 '
b0 *
b0 o
1#
#100000
0#
#105000
b11000011100 0
b11000011100 >
b11000011100 S
b0 X
b0 _
b0 j
b11000011100 /
b11000011100 Q
b11000011100 W
b11000011100 m
b0 Y
b0 f
b0 g
b11000011100011110000010 \
b11000011100011110000010 b
b11000011100011110000010 k
b1 O
b101001 3
b101001 I
b101001 r
1:
b11 5
b11 N
b11 U
b11 ^
b1000 J
b111 (
1#
#110000
0#
#115000
b11111111111000001110000000000000 X
b11111111111000001110000000000000 _
b11111111111000001110000000000000 j
b1 8
b1 ?
b1 L
b10 O
06
b1 5
b1 N
b1 U
b1 ^
0:
b1001 J
b1111111000001110 -
b1111111000001110 [
b1111111000001110 h
b1111111000001110 u
b0 a
b1000 (
b1 )
1#
#120000
0#
#125000
b0 X
b0 _
b0 j
b11111111111000001110000000000000 a
b11 O
b101 1
b101 P
b101 s
16
b1010 J
b100000000 .
b100000000 Z
b100000000 d
b100000000 q
b100000000 '
b100000000 *
b100000000 o
b1001 (
1#
#130000
0#
#135000
b11111111111110011111001000000000 X
b11111111111110011111001000000000 _
b11111111111110011111001000000000 j
b100 O
b110 1
b110 P
b110 s
b1011 J
b1111111011011100 ,
b1111111011011100 V
b1111111011011100 c
b1111111011011100 v
b11111111111110011111001000000000 Y
b11111111111110011111001000000000 f
b11111111111110011111001000000000 g
b1110111010 .
b1110111010 Z
b1110111010 d
b1110111010 q
b1010 (
b1110111010 '
b1110111010 *
b1110111010 o
1#
#140000
0#
#145000
b11111111111110111011111111011000 X
b11111111111110111011111111011000 _
b11111111111110111011111111011000 j
b11111111111110111011111111011000 Y
b11111111111110111011111111011000 f
b11111111111110111011111111011000 g
b11111111110110101101001000000000 a
b1111011101110010 ,
b1111011101110010 V
b1111011101110010 c
b1111011101110010 v
b101 O
b111 1
b111 P
b111 s
b1100 J
b100010010100 .
b100010010100 Z
b100010010100 d
b100010010100 q
b100010010100 '
b100010010100 *
b100010010100 o
b1011 (
1#
#150000
0#
#155000
b11111111101101101001110111101000 X
b11111111101101101001110111101000 _
b11111111101101101001110111101000 j
b110 O
b1000 1
b1000 P
b1000 s
b1101 J
b1000111110 ,
b1000111110 V
b1000111110 c
b1000111110 v
b11111111110101101001000111011000 a
b11111111101101101001110111101000 Y
b11111111101101101001110111101000 f
b11111111101101101001110111101000 g
b100110110000 .
b100110110000 Z
b100110110000 d
b100110110000 q
b1100 (
b100110110000 '
b100110110000 *
b100110110000 o
1#
#160000
0#
#165000
b101011011100010100000 X
b101011011100010100000 _
b101011011100010100000 j
b101011011100010100000 Y
b101011011100010100000 f
b101011011100010100000 g
b11111111100011010010111111000000 a
b1111111110001101 ,
b1111111110001101 V
b1111111110001101 c
b1111111110001101 v
b111 O
b10 5
b10 N
b10 U
b10 ^
b1110 J
b0 .
b0 Z
b0 d
b0 q
b0 '
b0 *
b0 o
b1101 (
1#
#170000
0#
#175000
b0 0
b0 >
b0 S
b0 /
b0 Q
b0 W
b0 m
b0 X
b0 _
b0 j
b1 O
b101010 3
b101010 I
b101010 r
1:
b11 5
b11 N
b11 U
b11 ^
b1111 J
b11111111100011010010111111000000 \
b11111111100011010010111111000000 b
b11111111100011010010111111000000 k
b0 Y
b0 f
b0 g
b1110 (
1#
#180000
0#
#185000
b11111111110100111101000000000000 X
b11111111110100111101000000000000 _
b11111111110100111101000000000000 j
b0 a
b1111110100111101 -
b1111110100111101 [
b1111110100111101 h
b1111110100111101 u
b10 8
b10 ?
b10 L
b10 O
06
b1 5
b1 N
b1 U
b1 ^
0:
b10000 J
b10 )
b1111 (
1#
#190000
0#
#195000
b0 X
b0 _
b0 j
b11 O
b1001 1
b1001 P
b1001 s
16
b10001 J
b11111111110100111101000000000000 a
b100000000 .
b100000000 Z
b100000000 d
b100000000 q
b10000 (
b100000000 '
b100000000 *
b100000000 o
1#
#200000
0#
#205000
b11111111111111111000110100000000 X
b11111111111111111000110100000000 _
b11111111111111111000110100000000 j
b11111111111111111000110100000000 Y
b11111111111111111000110100000000 f
b11111111111111111000110100000000 g
b1010101010 ,
b1010101010 V
b1010101010 c
b1010101010 v
b100 O
b1010 1
b1010 P
b1010 s
b10010 J
b1110111010 .
b1110111010 Z
b1110111010 d
b1110111010 q
b1110111010 '
b1110111010 *
b1110111010 o
b10001 (
1#
#210000
0#
#215000
b10011110110110000100 X
b10011110110110000100 _
b10011110110110000100 j
b101 O
b1011 1
b1011 P
b1011 s
b10011 J
b1111110111101010 ,
b1111110111101010 V
b1111110111101010 c
b1111110111101010 v
b11111111110100110101110100000000 a
b10011110110110000100 Y
b10011110110110000100 f
b10011110110110000100 g
b100010010100 .
b100010010100 Z
b100010010100 d
b100010010100 q
b10010 (
b100010010100 '
b100010010100 *
b100010010100 o
1#
#220000
0#
#225000
b11111111111011100001101101001000 X
b11111111111011100001101101001000 _
b11111111111011100001101101001000 j
b11111111111011100001101101001000 Y
b11111111111011100001101101001000 f
b11111111111011100001101101001000 g
b11111111110111010100101010000100 a
b11100000 ,
b11100000 V
b11100000 c
b11100000 v
b110 O
b1100 1
b1100 P
b1100 s
b10100 J
b100110110000 .
b100110110000 Z
b100110110000 d
b100110110000 q
b100110110000 '
b100110110000 *
b100110110000 o
b10011 (
1#
#230000
0#
#235000
b10000111101000000000 X
b10000111101000000000 _
b10000111101000000000 j
b111 O
b10 5
b10 N
b10 U
b10 ^
b10101 J
b1011000111 ,
b1011000111 V
b1011000111 c
b1011000111 v
b11111111110010110110010111001100 a
b10000111101000000000 Y
b10000111101000000000 f
b10000111101000000000 g
b0 .
b0 Z
b0 d
b0 q
b10100 (
b0 '
b0 *
b0 o
1#
#240000
0#
#245000
b0 X
b0 _
b0 j
b0 Y
b0 f
b0 g
b11111111110010110110010111001100 \
b11111111110010110110010111001100 b
b11111111110010110110010111001100 k
b1 O
b101011 3
b101011 I
b101011 r
1:
b11 5
b11 N
b11 U
b11 ^
b10110 J
b10101 (
1#
#250000
0#
#255000
b1000000110101000000000000 X
b1000000110101000000000000 _
b1000000110101000000000000 j
b11 8
b11 ?
b11 L
b10 O
06
b1 5
b1 N
b1 U
b1 ^
0:
b10111 J
b1000000110101 -
b1000000110101 [
b1000000110101 h
b1000000110101 u
b0 a
b10110 (
b11 )
1#
#260000
0#
#265000
b0 X
b0 _
b0 j
b1000000110101000000000000 a
b11 O
b1101 1
b1101 P
b1101 s
16
b11000 J
b100000000 .
b100000000 Z
b100000000 d
b100000000 q
b100000000 '
b100000000 *
b100000000 o
b10111 (
1#
#270000
0#
#275000
b101100011100000000 X
b101100011100000000 _
b101100011100000000 j
b100 O
b1110 1
b1110 P
b1110 s
b11001 J
b1111001111011001 ,
b1111001111011001 V
b1111001111011001 c
b1111001111011001 v
b101100011100000000 Y
b101100011100000000 f
b101100011100000000 g
b1110111010 .
b1110111010 Z
b1110111010 d
b1110111010 q
b11000 (
b1110111010 '
b1110111010 *
b1110111010 o
1#
#280000
0#
